setup.py
bfillings/__init__.py
bfillings/align.py
bfillings/blast.py
bfillings/blat.py
bfillings/bwa.py
bfillings/cd_hit.py
bfillings/clearcut.py
bfillings/clustalw.py
bfillings/denoiser.py
bfillings/fastq_join.py
bfillings/fasttree.py
bfillings/fasttree_v1.py
bfillings/formatdb.py
bfillings/infernal.py
bfillings/mafft.py
bfillings/mothur.py
bfillings/muscle_v38.py
bfillings/parsinsert.py
bfillings/pplacer.py
bfillings/raxml_v730.py
bfillings/rdp_classifier.py
bfillings/rtax.py
bfillings/seqprep.py
bfillings/sortmerna_v2.py
bfillings/sumaclust_v1.py
bfillings/swarm_v127.py
bfillings/uclust.py
bfillings/usearch.py
bfillings/vsearch.py
bfillings/tests/__init__.py
bfillings/tests/test_blast.py
bfillings/tests/test_blat.py
bfillings/tests/test_bwa.py
bfillings/tests/test_cd_hit.py
bfillings/tests/test_clearcut.py
bfillings/tests/test_clustalw.py
bfillings/tests/test_fasttree.py
bfillings/tests/test_fasttree_v1.py
bfillings/tests/test_formatdb.py
bfillings/tests/test_infernal.py
bfillings/tests/test_mafft.py
bfillings/tests/test_mothur.py
bfillings/tests/test_muscle_v38.py
bfillings/tests/test_parsinsert.py
bfillings/tests/test_pplacer.py
bfillings/tests/test_raxml_v730.py
bfillings/tests/test_rdp_classifier.py
bfillings/tests/test_rtax.py
bfillings/tests/test_sortmerna_v2.py
bfillings/tests/test_sumaclust_v1.py
bfillings/tests/test_swarm_v127.py
bfillings/tests/test_uclust.py
bfillings/tests/test_usearch.py
bfillings/tests/test_vsearch.py
burrito_fillings.egg-info/PKG-INFO
burrito_fillings.egg-info/SOURCES.txt
burrito_fillings.egg-info/dependency_links.txt
burrito_fillings.egg-info/requires.txt
burrito_fillings.egg-info/top_level.txt