Metadata-Version: 1.1
Name: burrito-fillings
Version: 0.1.1
Summary: burrito-fillings: burrito application controllers for bioinformatics
Home-page: https://github.com/biocore/burrito-fillings
Author: biocore
Author-email: gregcaporaso@gmail.com
License: BSD
Platform: UNKNOWN
Classifier: Development Status :: 1 - Planning
Classifier: License :: OSI Approved :: BSD License
Classifier: Topic :: Software Development :: Libraries
Classifier: Topic :: Scientific/Engineering
Classifier: Topic :: Scientific/Engineering :: Bio-Informatics
Classifier: Programming Language :: Python
Classifier: Programming Language :: Python :: 2.7
Classifier: Operating System :: Unix
Classifier: Operating System :: POSIX
Classifier: Operating System :: MacOS :: MacOS X
